tests/__init__.py
tests/pytests/__init__.py
fastybird_fb_bus_connector/types.py
fastybird_fb_bus_connector/py.typed
fastybird_fb_bus_connector/logger.py
fastybird_fb_bus_connector/exceptions.py
fastybird_fb_bus_connector/connector.py
fastybird_fb_bus_connector/entities.py
fastybird_fb_bus_connector/__init__.py
fastybird_fb_bus_connector/bootstrap.py
fastybird_fb_bus_connector/receivers/receiver.py
fastybird_fb_bus_connector/receivers/apiv1.py
fastybird_fb_bus_connector/receivers/__init__.py
fastybird_fb_bus_connector/clients/apiv1.py
fastybird_fb_bus_connector/clients/client.py
fastybird_fb_bus_connector/clients/__init__.py
fastybird_fb_bus_connector/transporters/transporter.py
fastybird_fb_bus_connector/transporters/pjon.py
fastybird_fb_bus_connector/transporters/__init__.py
fastybird_fb_bus_connector/events/listeners.py
fastybird_fb_bus_connector/events/events.py
fastybird_fb_bus_connector/events/__init__.py
fastybird_fb_bus_connector/consumers/device.py
fastybird_fb_bus_connector/consumers/consumer.py
fastybird_fb_bus_connector/consumers/entities.py
fastybird_fb_bus_connector/consumers/__init__.py
fastybird_fb_bus_connector/registry/model.py
fastybird_fb_bus_connector/registry/__init__.py
fastybird_fb_bus_connector/registry/records.py
fastybird_fb_bus_connector/api/v1parser.py
fastybird_fb_bus_connector/api/v1builder.py
fastybird_fb_bus_connector/api/transformers.py
fastybird_fb_bus_connector/api/v1validator.py
fastybird_fb_bus_connector/api/__init__.py
fastybird_fb_bus_connector/pjon/_pjon.cpython-38-x86_64-linux-gnu.so
fastybird_fb_bus_connector/pjon/__init__.py
fastybird_fb_bus_connector-0.54.0.dist-info/top_level.txt
fastybird_fb_bus_connector-0.54.0.dist-info/WHEEL
fastybird_fb_bus_connector-0.54.0.dist-info/METADATA
fastybird_fb_bus_connector-0.54.0.dist-info/LICENSE.md
fastybird_fb_bus_connector-0.54.0.dist-info/RECORD
